genos/__init__.py
genos/instantiate.py
genos/version.py
genos/examples/__init__.py
genos/examples/complex_examples.py
genos/examples/simple_examples.py
genos-0.1.12.dist-info/LICENSE
genos-0.1.12.dist-info/METADATA
genos-0.1.12.dist-info/WHEEL
genos-0.1.12.dist-info/top_level.txt
genos-0.1.12.dist-info/RECORD
