Metadata-Version: 2.1
Name: genos
Version: 0.1.12
Summary: Instantiate objects and call functions using dictionary configs in Python using Genos.
Home-page: https://github.com/Neural-Space/genos
Author: Kushal Jain
Author-email: kushal@neuralspace.ai
License: MIT
Keywords: instantiation,objects,recursive instantiation,functio call,config instantiate
Classifier: Development Status :: 4 - Beta
Classifier: Intended Audience :: Developers
Classifier: License :: OSI Approved :: MIT License
Classifier: Topic :: Software Development :: Build Tools
Classifier: Topic :: Software Development :: Libraries :: Python Modules
Classifier: Topic :: Internet
Classifier: Programming Language :: Python :: 3.7
Requires-Python: >=3.7, <4
License-File: LICENSE
Requires-Dist: omegaconf (>=2.3.0)
